Metadata-Version: 2.1
Name: treeviz
Version: 1.1
Summary: Print tree in bash manner
Home-page: https://github.com/tsupei/treeviz
Author: Chen Tsu Pei
Author-email: a5560648@gmail.com
License: MIT
Download-URL: https://github.com/tsupei/treeviz/archive/v1.1.tar.gz
Keywords: tree,treeviz
Platform: UNKNOWN
